bronx/__init__.py
bronx/compat/__init__.py
bronx/compat/functools.py
bronx/compat/itertools.py
bronx/compat/moves.py
bronx/compat/random.py
bronx/datagrip/__init__.py
bronx/datagrip/datastore.py
bronx/datagrip/misc.py
bronx/datagrip/namelist.py
bronx/datagrip/netcdf.py
bronx/datagrip/pyexttiff.py
bronx/datagrip/varbc.py
bronx/datagrip/varbcheaders.py
bronx/fancies/__init__.py
bronx/fancies/colors.py
bronx/fancies/display.py
bronx/fancies/dump.py
bronx/fancies/language.py
bronx/fancies/loggers.py
bronx/graphics/__init__.py
bronx/graphics/axes.py
bronx/graphics/colormapping.py
bronx/meteo/__init__.py
bronx/meteo/constants.py
bronx/meteo/conversion.py
bronx/meteo/thermo.py
bronx/net/__init__.py
bronx/net/netrc.py
bronx/patterns/__init__.py
bronx/patterns/getbytag.py
bronx/patterns/observer.py
bronx/stdtypes/__init__.py
bronx/stdtypes/catalog.py
bronx/stdtypes/date.py
bronx/stdtypes/dictionaries.py
bronx/stdtypes/history.py
bronx/stdtypes/tracking.py
bronx/stdtypes/xtemplates.py
bronx/syntax/__init__.py
bronx/syntax/arrays.py
bronx/syntax/decorators.py
bronx/syntax/externalcode.py
bronx/syntax/iterators.py
bronx/syntax/minieval.py
bronx/syntax/parsing.py
bronx/syntax/pretty.py
bronx/system/__init__.py
bronx/system/cpus.py
bronx/system/hash.py
bronx/system/interrupt.py
bronx/system/memory.py
bronx/system/mf.py
bronx/system/numa.py
bronx/system/unistd.py
bronx_beta-2.0.0b2.dist-info/LICENSE-en.txt
bronx_beta-2.0.0b2.dist-info/LICENSE.txt
bronx_beta-2.0.0b2.dist-info/METADATA
bronx_beta-2.0.0b2.dist-info/WHEEL
bronx_beta-2.0.0b2.dist-info/top_level.txt
bronx_beta-2.0.0b2.dist-info/RECORD
